<edmx:Edmx xmlns:edmx="http://docs.oasis-open.org/odata/ns/edmx" Version="4.0">
    <edmx:Reference Uri="https://oasis-tcs.github.io/odata-vocabularies/vocabularies/Org.OData.Capabilities.V1.xml">
        <edmx:Include Namespace="Org.OData.Capabilities.V1" Alias="Capabilities"/>
    </edmx:Reference>
    <edmx:Reference Uri="https://sap.github.io/odata-vocabularies/vocabularies/Common.xml">
        <edmx:Include Namespace="com.sap.vocabularies.Common.v1" Alias="Common"/>
    </edmx:Reference>
    <edmx:Reference Uri="https://sap.github.io/odata-vocabularies/vocabularies/UI.xml">
        <edmx:Include Namespace="com.sap.vocabularies.UI.v1" Alias="UI"/>
    </edmx:Reference>
    <edmx:Reference Uri="/api/v2/odata.svc/">
        <edmx:Include Namespace="com.agel.mmts.entity"/>
    </edmx:Reference>
    <edmx:DataServices>
        <Schema xmlns="http://docs.oasis-open.org/odata/ns/edm" Namespace="com.agel.mmts">
        <Annotations Target="com.agel.mmts.entity.PurchaseOrderModel">
            <Annotation Term="Capabilities.InsertRestrictions">
                <Record Type="Capabilities.InsertRestrictionsType">
                    <PropertyValue Property="Insertable" Bool="false"></PropertyValue>
                </Record>
            </Annotation>
        </Annotations>
        <Annotations Target="com.agel.mmts.entity.PurchaseOrderModel">
            <Annotation Term="UI.DeleteHidden" Bool="true"/>
        </Annotations>
            <Annotations Target="com.agel.mmts.entity.PurchaseOrderModel">
                <Annotation Term="Common.SemanticKey">
                    <Collection>
                        <PropertyPath>PONumber</PropertyPath>
                    </Collection>
                </Annotation>
                <Annotation Term="UI.LineItem">
                    <Collection>
                        <Record Type="UI.DataField">
                            <PropertyValue Property="Value" Path="PONumber"/>
                        </Record>
                        <Record Type="UI.DataField">
                            <PropertyValue Property="Value" Path="PlantCode"/>
                        </Record>
                        <Record Type="UI.DataField">
                            <PropertyValue Property="Value" Path="CreatedAt"/>
                        </Record>
                        <Record Type="UI.DataField">
                            <PropertyValue Property="Value" Path="POReleaseDate"/>
                        </Record>
                        <Record Type="UI.DataField">
                            <PropertyValue Property="Value" Path="ConfirmedDate"/>
                        </Record>
                        <Record Type="UI.DataField">
                            <PropertyValue Property="Value" Path="Buyer/CompanyCode"/>
                        </Record>
                        <Record Type="UI.DataField">
                            <PropertyValue Property="Value" Path="Vendor/Name"/>
                        </Record>
                        <Record Type="UI.DataField">
                            <PropertyValue Property="Value" Path="Status"/>
                        </Record>
                    </Collection>
                </Annotation>
            </Annotations>
            <Annotations Target="com.agel.mmts.entity.PurchaseOrderModel/PONumber">
                <Annotation Term="Common.Label" String="{@i18n>poNumber}"/>
            </Annotations>
            <Annotations Target="com.agel.mmts.entity.PurchaseOrderModel/PlantCode">
                <Annotation Term="Common.Label" String="{@i18n>plantCode}"/>
            </Annotations>
            <Annotations Target="com.agel.mmts.entity.PurchaseOrderModel/CreatedAt">
                <Annotation Term="Common.Label" String="{@i18n>createdOn}"/>
            </Annotations>
            <Annotations Target="com.agel.mmts.entity.PurchaseOrderModel/POReleaseDate">
                <Annotation Term="Common.Label" String="{@i18n>releasedOn}"/>
            </Annotations>
            <Annotations Target="com.agel.mmts.entity.PurchaseOrderModel/ConfirmedDate">
                <Annotation Term="Common.Label" String="{@i18n>confirmedOn}"/>
            </Annotations>
            <Annotations Target="com.agel.mmts.entity.BuyerModel/CompanyCode">
                <Annotation Term="Common.Label" String="{@i18n>companyCode}"/>
            </Annotations>
            <Annotations Target="com.agel.mmts.entity.VendorModel/Name">
                <Annotation Term="Common.Label" String="{@i18n>vendor}"/>
            </Annotations>
            <Annotations Target="com.agel.mmts.entity.VendorModel/VendorCode">
                <Annotation Term="Common.Label" String="{@i18n>vendorCode}"/>
            </Annotations>
            <Annotations Target="com.agel.mmts.entity.PurchaseOrderModel/Status">
                <Annotation Term="Common.Label" String="{@i18n>status}"/>
            </Annotations>
            <Annotations Target="com.agel.mmts.entity.PurchaseOrderModel">
                <Annotation Term="UI.HeaderInfo">
                    <Record Type="UI.HeaderInfoType">
                        <PropertyValue Property="TypeName" String="{@i18n>purchaseOrder}"/>
                        <PropertyValue Property="TypeNamePlural" String="{@i18n>purchaseOrders}"/>
                    </Record>
                </Annotation>
                <Annotation Term="UI.SelectionFields">
                    <Collection>
                        <PropertyPath>PONumber</PropertyPath>
                        <PropertyPath>PlantCode</PropertyPath>
                        <PropertyPath>Buyer/CompanyCode</PropertyPath>
                        <PropertyPath>Vendor/Name</PropertyPath>
                        <PropertyPath>Vendor/VendorCode</PropertyPath>
                        <PropertyPath>Status</PropertyPath>
                    </Collection>
                </Annotation>
            </Annotations>
        </Schema>
    </edmx:DataServices>
</edmx:Edmx>