<mvc:View xmlns:mvc="sap.ui.core.mvc"
    xmlns:core="sap.ui.core"
    xmlns:f="sap.ui.layout.form"
    xmlns="sap.m">

    <f:SimpleForm layout="ColumnLayout" columnsM="2" columnsL="4" columnsXL="4" binding="{Buyer}" singleContainerFullSize="true" class="style-RemoveTitleHeight">
        <f:content>
            <!-- <core:Title  /> -->
            <Label text="{i18n>ContractorName}" />
            <Text text="{ContactPerson}" />
            <Label text="{i18n>ContractorId}" />
            <Text text="{BuyerCode}" />
             <Label text="{i18n>PlantSite-Location}" />
            <Text text="{GSTIN}"/>
            <Label text="{i18n>ActivePeriod}" />
            <Text text="{Pan}"/>
            
            <!-- <core:Title /> -->
            <Label text="{i18n>Materials}" />
            <ExpandableText binding="{Address}" text="{parts: [{path: 'Street'}, {path: 'City'}, {path: 'State'}, {path: 'Country'}, {path: 'pinCode'}]}" 
            overflowMode="InPlace"/>
              <Label text="{i18n>Description}" />
            <Text text="{PurchasingOrg}"/>
            <Label text="{i18n>Service-Covered}" />
            <Text text="{PurchasingGroup}"/>
            
        </f:content>
    </f:SimpleForm>

</mvc:View>
